<?xml version="1.0" encoding="euc-jp"?>

<response>

  <request>

    <parameters>

      <parameter name="api_id" value="apiaccount" />

      <parameter name="affiliate_id" value="affiliate-999" />

      <parameter name="operation" value="ItemList" />

      <parameter name="version" value="2.00" />

      <parameter name="timestamp" value="2012-12-01 00:00:00" />

      <parameter name="site" value="DMM.co.jp" />

      <parameter name="service" value="ppm" />

      <parameter name="keyword" value="ギリギリモザイク" />

    </parameters>

  </request>

  <result>

    <result_count>20</result_count>

    <total_count>47</total_count>

    <first_position>1</first_position>

    <items>

      <item>

        <service_name>1円動画</service_name>

        <floor_name>ビデオ</floor_name>

        <category_name>ビデオ (1円動画)</category_name>

        <content_id>soe206</content_id>

        <product_id>soe00206</product_id>

        <title>了解×新人×ギリモザ パーフェクトボディ 桜ここみ</title>

        <URL>http://www.dmm.co.jp/ppm/video/-/detail/=/cid=soe206/</URL>

        <affiliateURL>http://www.dmm.co.jp/ppm/video/-/detail/=/cid=soe206/affiliate-999</affiliateURL>

        <imageURL>

          <list>http://pics.dmm.co.jp/digital/video/soe00206/soe00206pt.jpg</list>

          <small>http://pics.dmm.co.jp/digital/video/soe00206/soe00206ps.jpg</small>

          <large>http://pics.dmm.co.jp/digital/video/soe00206/soe00206pl.jpg</large>

        </imageURL>

        <prices>

          <price>70</price>

        </prices>

        <date>2009-07-17 10:00:28</date>

        <iteminfo>

          <keyword>

            <name>独占配信</name>

            <id>6548</id>

          </keyword>

          <keyword>

            <name>拘束</name>

            <id>25</id>

          </keyword>

          <keyword>

            <name>単体作品</name>

            <id>4025</id>

          </keyword>

          <keyword>

            <name>潮吹き</name>

            <id>5016</id>

          </keyword>

          <keyword>

            <name>顔射</name>

            <id>5023</id>

          </keyword>

          <keyword>

            <name>ギリモザ</name>

            <id>6017</id>

          </keyword>

          <series>

            <name>新人×ギリギリモザイク</name>

            <id>3454</id>

          </series>

          <maker>

            <name>エスワン ナンバーワンスタイル</name>

            <id>3152</id>

          </maker>

          <actress>

            <name>桜ここみ</name>

            <id>27643</id>

          </actress>

          <actress>

            <name>さくらここみ</name>

            <id>27643_ruby</id>

          </actress>

          <actress>

            <name>av</name>

            <id>27643_classify</id>

          </actress>

          <director>

            <name>坂東清四郎</name>

            <id>101311</id>

          </director>

          <director>

            <name>ばんどうせいしろう</name>

            <id>101311_ruby</id>

          </director>

          <label>

            <name>S1 NO.1 STYLE</name>

            <id>3474</id>

          </label>

        </iteminfo>

      </item>

      <item>

        <service_name>1円動画</service_name>

        <floor_name>ビデオ</floor_name>

        <category_name>ビデオ (1円動画)</category_name>

        <content_id>onsd204</content_id>

        <product_id>onsd00204</product_id>

        <title>ハイパーギリギリモザイク8時間 小倉ありす</title>

        <URL>http://www.dmm.co.jp/ppm/video/-/detail/=/cid=onsd204/</URL>

        <affiliateURL>http://www.dmm.co.jp/ppm/video/-/detail/=/cid=onsd204/affiliate-999</affiliateURL>

        <imageURL>

          <list>http://pics.dmm.co.jp/digital/video/onsd00204/onsd00204pt.jpg</list>

          <small>http://pics.dmm.co.jp/digital/video/onsd00204/onsd00204ps.jpg</small>

          <large>http://pics.dmm.co.jp/digital/video/onsd00204/onsd00204pl.jpg</large>

        </imageURL>

        <prices>

          <price>70</price>

        </prices>

        <date>2008-11-12 10:00:00</date>

        <iteminfo>

          <keyword>

            <name>独占配信</name>

            <id>6548</id>

          </keyword>

          <keyword>

            <name>ギリモザ</name>

            <id>6017</id>

          </keyword>

          <keyword>

            <name>淫語</name>

            <id>5025</id>

          </keyword>

          <keyword>

            <name>コスプレ</name>

            <id>4031</id>

          </keyword>

          <keyword>

            <name>ロリ系</name>

            <id>2008</id>

          </keyword>

          <series>

            <name>S1 GIRLS COLLECTION</name>

            <id>5087</id>

          </series>

          <maker>

            <name>エスワン ナンバーワンスタイル</name>

            <id>3152</id>

          </maker>

          <actress>

            <name>小倉ありす</name>

            <id>7014</id>

          </actress>

          <actress>

            <name>おぐらありす</name>

            <id>7014_ruby</id>

          </actress>

          <actress>

            <name>av</name>

            <id>7014_classify</id>

          </actress>

          <label>

            <name>S1 NO.1 STYLE</name>

            <id>3474</id>

          </label>

        </iteminfo>

      </item>

      <item>

        <service_name>1円動画</service_name>

        <floor_name>ビデオ</floor_name>

        <category_name>ビデオ (1円動画)</category_name>

        <content_id>soe021</content_id>

        <product_id>soe00021</product_id>

        <title>解禁×ハイパー×ギリモザ ハイパーギリモザ 佐山愛</title>

        <URL>http://www.dmm.co.jp/ppm/video/-/detail/=/cid=soe021/</URL>

        <affiliateURL>http://www.dmm.co.jp/ppm/video/-/detail/=/cid=soe021/affiliate-999</affiliateURL>

        <imageURL>

          <list>http://pics.dmm.co.jp/digital/video/soe00021/soe00021pt.jpg</list>

          <small>http://pics.dmm.co.jp/digital/video/soe00021/soe00021ps.jpg</small>

          <large>http://pics.dmm.co.jp/digital/video/soe00021/soe00021pl.jpg</large>

        </imageURL>

        <prices>

          <price>70</price>

        </prices>

        <date>2008-11-12 10:00:51</date>

        <iteminfo>

          <keyword>

            <name>巨乳</name>

            <id>2001</id>

          </keyword>

          <keyword>

            <name>潮吹き</name>

            <id>5016</id>

          </keyword>

          <keyword>

            <name>パイズリ</name>

            <id>5019</id>

          </keyword>

          <keyword>

            <name>3P・4P</name>

            <id>5022</id>

          </keyword>

          <keyword>

            <name>ギリモザ</name>

            <id>6017</id>

          </keyword>

          <keyword>

            <name>独占配信</name>

            <id>6548</id>

          </keyword>

          <series>

            <name>ハイパーギリギリモザイク</name>

            <id>6542</id>

          </series>

          <maker>

            <name>エスワン ナンバーワンスタイル</name>

            <id>3152</id>

          </maker>

          <actress>

            <name>佐山愛</name>

            <id>21549</id>

          </actress>

          <actress>

            <name>さやまあい</name>

            <id>21549_ruby</id>

          </actress>

          <actress>

            <name>av</name>

            <id>21549_classify</id>

          </actress>

          <director>

            <name>秋秀人</name>

            <id>101149</id>

          </director>

          <director>

            <name>あきひでと</name>

            <id>101149_ruby</id>

          </director>

          <label>

            <name>S1 NO.1 STYLE</name>

            <id>3474</id>

          </label>

        </iteminfo>

      </item>

      <item>

        <service_name>1円動画</service_name>

        <floor_name>ビデオ</floor_name>

        <category_name>ビデオ (1円動画)</category_name>

        <content_id>1sdms556</content_id>

        <product_id>1sdms00556</product_id>

        <title>素人娘がギリギリモザイクフェラで最後はザーメン口内発射！2</title>

        <URL>http://www.dmm.co.jp/ppm/video/-/detail/=/cid=1sdms556/</URL>

        <affiliateURL>http://www.dmm.co.jp/ppm/video/-/detail/=/cid=1sdms556/affiliate-999</affiliateURL>

        <imageURL>

          <list>http://pics.dmm.co.jp/digital/video/1sdms00556/1sdms00556pt.jpg</list>

          <small>http://pics.dmm.co.jp/digital/video/1sdms00556/1sdms00556ps.jpg</small>

          <large>http://pics.dmm.co.jp/digital/video/1sdms00556/1sdms00556pl.jpg</large>

        </imageURL>

        <prices>

          <price>30</price>

        </prices>

        <date>2009-04-09 10:00:12</date>

        <iteminfo>

          <keyword>

            <name>企画</name>

            <id>4007</id>

          </keyword>

          <keyword>

            <name>ナンパ</name>

            <id>4006</id>

          </keyword>

          <keyword>

            <name>フェラ</name>

            <id>5002</id>

          </keyword>

          <keyword>

            <name>素人</name>

            <id>4024</id>

          </keyword>

          <series>

            <name>素人娘</name>

            <id>70867</id>

          </series>

          <maker>

            <name>SODクリエイト</name>

            <id>45276</id>

          </maker>

          <director>

            <name>藤丼博之</name>

            <id>102823</id>

          </director>

          <director>

            <name>ふじどんひろゆき</name>

            <id>102823_ruby</id>

          </director>

          <label>

            <name>SOFT ON DEMAND</name>

            <id>125</id>

          </label>

        </iteminfo>

      </item>

      <item>

        <service_name>1円動画</service_name>

        <floor_name>ビデオ</floor_name>

        <category_name>ビデオ (1円動画)</category_name>

        <content_id>soe013</content_id>

        <product_id>soe00013</product_id>

        <title>ハイパー×ギリモザ ハイパーギリモザ 初音みのり</title>

        <URL>http://www.dmm.co.jp/ppm/video/-/detail/=/cid=soe013/</URL>

        <affiliateURL>http://www.dmm.co.jp/ppm/video/-/detail/=/cid=soe013/affiliate-999</affiliateURL>

        <imageURL>

          <list>http://pics.dmm.co.jp/digital/video/soe00013/soe00013pt.jpg</list>

          <small>http://pics.dmm.co.jp/digital/video/soe00013/soe00013ps.jpg</small>

          <large>http://pics.dmm.co.jp/digital/video/soe00013/soe00013pl.jpg</large>

        </imageURL>

        <prices>

          <price>70</price>

        </prices>

        <date>2008-11-12 10:00:00</date>

        <iteminfo>

          <keyword>

            <name>ギリモザ</name>

            <id>6017</id>

          </keyword>

          <keyword>

            <name>独占配信</name>

            <id>6548</id>

          </keyword>

          <keyword>

            <name>巨乳</name>

            <id>2001</id>

          </keyword>

          <keyword>

            <name>潮吹き</name>

            <id>5016</id>

          </keyword>

          <keyword>

            <name>パイズリ</name>

            <id>5019</id>

          </keyword>

          <series>

            <name>ハイパーギリギリモザイク</name>

            <id>6542</id>

          </series>

          <maker>

            <name>エスワン ナンバーワンスタイル</name>

            <id>3152</id>

          </maker>

          <actress>

            <name>初音みのり</name>

            <id>20214</id>

          </actress>

          <actress>

            <name>はつねみのり</name>

            <id>20214_ruby</id>

          </actress>

          <actress>

            <name>av</name>

            <id>20214_classify</id>

          </actress>

          <director>

            <name>秋秀人</name>

            <id>101149</id>

          </director>

          <director>

            <name>あきひでと</name>

            <id>101149_ruby</id>

          </director>

          <label>

            <name>S1 NO.1 STYLE</name>

            <id>3474</id>

          </label>

        </iteminfo>

      </item>

      <item>

        <service_name>1円動画</service_name>

        <floor_name>ビデオ</floor_name>

        <category_name>ビデオ (1円動画)</category_name>

        <content_id>soe006</content_id>

        <product_id>soe00006</product_id>

        <title>ギリギリモザイク 無限絶頂！激イカセFUCK 初音みのり</title>

        <URL>http://www.dmm.co.jp/ppm/video/-/detail/=/cid=soe006/</URL>

        <affiliateURL>http://www.dmm.co.jp/ppm/video/-/detail/=/cid=soe006/affiliate-999</affiliateURL>

        <imageURL>

          <list>http://pics.dmm.co.jp/digital/video/soe00006/soe00006pt.jpg</list>

          <small>http://pics.dmm.co.jp/digital/video/soe00006/soe00006ps.jpg</small>

          <large>http://pics.dmm.co.jp/digital/video/soe00006/soe00006pl.jpg</large>

        </imageURL>

        <prices>

          <price>70</price>

        </prices>

        <date>2008-11-12 10:00:00</date>

        <iteminfo>

          <keyword>

            <name>ギリモザ</name>

            <id>6017</id>

          </keyword>

          <keyword>

            <name>3P・4P</name>

            <id>5022</id>

          </keyword>

          <keyword>

            <name>拘束</name>

            <id>25</id>

          </keyword>

          <keyword>

            <name>巨乳</name>

            <id>2001</id>

          </keyword>

          <keyword>

            <name>独占配信</name>

            <id>6548</id>

          </keyword>

          <series>

            <name>無限絶頂！激イカセFUCK</name>

            <id>7145</id>

          </series>

          <maker>

            <name>エスワン ナンバーワンスタイル</name>

            <id>3152</id>

          </maker>

          <actress>

            <name>初音みのり</name>

            <id>20214</id>

          </actress>

          <actress>

            <name>はつねみのり</name>

            <id>20214_ruby</id>

          </actress>

          <actress>

            <name>av</name>

            <id>20214_classify</id>

          </actress>

          <director>

            <name>秋秀人</name>

            <id>101149</id>

          </director>

          <director>

            <name>あきひでと</name>

            <id>101149_ruby</id>

          </director>

          <label>

            <name>S1 NO.1 STYLE</name>

            <id>3474</id>

          </label>

        </iteminfo>

      </item>

      <item>

        <service_name>1円動画</service_name>

        <floor_name>ビデオ</floor_name>

        <category_name>ビデオ (1円動画)</category_name>

        <content_id>soe045</content_id>

        <product_id>soe00045</product_id>

        <title>ドスケベ×ギリモザ 新人ギリモザ 長月ラム</title>

        <URL>http://www.dmm.co.jp/ppm/video/-/detail/=/cid=soe045/</URL>

        <affiliateURL>http://www.dmm.co.jp/ppm/video/-/detail/=/cid=soe045/affiliate-999</affiliateURL>

        <imageURL>

          <list>http://pics.dmm.co.jp/digital/video/soe00045/soe00045pt.jpg</list>

          <small>http://pics.dmm.co.jp/digital/video/soe00045/soe00045ps.jpg</small>

          <large>http://pics.dmm.co.jp/digital/video/soe00045/soe00045pl.jpg</large>

        </imageURL>

        <prices>

          <price>70</price>

        </prices>

        <date>2008-11-19 10:00:40</date>

        <iteminfo>

          <keyword>

            <name>デビュー作品</name>

            <id>6006</id>

          </keyword>

          <keyword>

            <name>騎乗位</name>

            <id>4106</id>

          </keyword>

          <keyword>

            <name>潮吹き</name>

            <id>5016</id>

          </keyword>

          <keyword>

            <name>顔射</name>

            <id>5023</id>

          </keyword>

          <keyword>

            <name>ギリモザ</name>

            <id>6017</id>

          </keyword>

          <keyword>

            <name>独占配信</name>

            <id>6548</id>

          </keyword>

          <series>

            <name>新人×ギリギリモザイク</name>

            <id>3454</id>

          </series>

          <maker>

            <name>エスワン ナンバーワンスタイル</name>

            <id>3152</id>

          </maker>

          <actress>

            <name>長月ラム</name>

            <id>26611</id>

          </actress>

          <actress>

            <name>ながつきらむ</name>

            <id>26611_ruby</id>

          </actress>

          <actress>

            <name>av</name>

            <id>26611_classify</id>

          </actress>

          <director>

            <name>コハク碧</name>

            <id>101125</id>

          </director>

          <director>

            <name>こはくあおい</name>

            <id>101125_ruby</id>

          </director>

          <label>

            <name>S1 NO.1 STYLE</name>

            <id>3474</id>

          </label>

        </iteminfo>

      </item>

      <item>

        <service_name>1円動画</service_name>

        <floor_name>ビデオ</floor_name>

        <category_name>ビデオ (1円動画)</category_name>

        <content_id>soe00223</content_id>

        <product_id>soe00223</product_id>

        <title>了解×ギリモザ 新人ギリモザ 桐原エリカ</title>

        <URL>http://www.dmm.co.jp/ppm/video/-/detail/=/cid=soe00223/</URL>

        <affiliateURL>http://www.dmm.co.jp/ppm/video/-/detail/=/cid=soe00223/affiliate-999</affiliateURL>

        <imageURL>

          <list>http://pics.dmm.co.jp/digital/video/soe00223/soe00223pt.jpg</list>

          <small>http://pics.dmm.co.jp/digital/video/soe00223/soe00223ps.jpg</small>

          <large>http://pics.dmm.co.jp/digital/video/soe00223/soe00223pl.jpg</large>

        </imageURL>

        <prices>

          <price>70</price>

        </prices>

        <date>2009-08-19 10:00:22</date>

        <iteminfo>

          <keyword>

            <name>クンニ</name>

            <id>38</id>

          </keyword>

          <keyword>

            <name>巨乳</name>

            <id>2001</id>

          </keyword>

          <keyword>

            <name>手コキ</name>

            <id>5004</id>

          </keyword>

          <keyword>

            <name>潮吹き</name>

            <id>5016</id>

          </keyword>

          <keyword>

            <name>ギリモザ</name>

            <id>6017</id>

          </keyword>

          <keyword>

            <name>独占配信</name>

            <id>6548</id>

          </keyword>

          <series>

            <name>新人×ギリギリモザイク</name>

            <id>3454</id>

          </series>

          <maker>

            <name>エスワン ナンバーワンスタイル</name>

            <id>3152</id>

          </maker>

          <actress>

            <name>桐原エリカ</name>

            <id>28041</id>

          </actress>

          <actress>

            <name>きりはらえりか</name>

            <id>28041_ruby</id>

          </actress>

          <actress>

            <name>av</name>

            <id>28041_classify</id>

          </actress>

          <label>

            <name>S1 NO.1 STYLE</name>

            <id>3474</id>

          </label>

        </iteminfo>

      </item>

      <item>

        <service_name>1円動画</service_name>

        <floor_name>ビデオ</floor_name>

        <category_name>ビデオ (1円動画)</category_name>

        <content_id>soe018</content_id>

        <product_id>soe00018</product_id>

        <title>了解×ギリモザ 新人ギリモザ 鮎川あゆみ</title>

        <URL>http://www.dmm.co.jp/ppm/video/-/detail/=/cid=soe018/</URL>

        <affiliateURL>http://www.dmm.co.jp/ppm/video/-/detail/=/cid=soe018/affiliate-999</affiliateURL>

        <imageURL>

          <list>http://pics.dmm.co.jp/digital/video/soe00018/soe00018pt.jpg</list>

          <small>http://pics.dmm.co.jp/digital/video/soe00018/soe00018ps.jpg</small>

          <large>http://pics.dmm.co.jp/digital/video/soe00018/soe00018pl.jpg</large>

        </imageURL>

        <prices>

          <price>70</price>

        </prices>

        <date>2008-11-12 10:01:05</date>

        <iteminfo>

          <keyword>

            <name>巨乳</name>

            <id>2001</id>

          </keyword>

          <keyword>

            <name>パイズリ</name>

            <id>5019</id>

          </keyword>

          <keyword>

            <name>潮吹き</name>

            <id>5016</id>

          </keyword>

          <keyword>

            <name>3P・4P</name>

            <id>5022</id>

          </keyword>

          <keyword>

            <name>ギリモザ</name>

            <id>6017</id>

          </keyword>

          <keyword>

            <name>独占配信</name>

            <id>6548</id>

          </keyword>

          <series>

            <name>新人×ギリギリモザイク</name>

            <id>3454</id>

          </series>

          <maker>

            <name>エスワン ナンバーワンスタイル</name>

            <id>3152</id>

          </maker>

          <actress>

            <name>鮎川あゆみ</name>

            <id>24128</id>

          </actress>

          <actress>

            <name>あゆかわあゆみ</name>

            <id>24128_ruby</id>

          </actress>

          <actress>

            <name>av</name>

            <id>24128_classify</id>

          </actress>

          <director>

            <name>椿一刀</name>

            <id>101286</id>

          </director>

          <director>

            <name>つばきいっとう</name>

            <id>101286_ruby</id>

          </director>

          <label>

            <name>S1 NO.1 STYLE</name>

            <id>3474</id>

          </label>

        </iteminfo>

      </item>

      <item>

        <service_name>1円動画</service_name>

        <floor_name>ビデオ</floor_name>

        <category_name>ビデオ (1円動画)</category_name>

        <content_id>soe077</content_id>

        <product_id>soe00077</product_id>

        <title>新人×ギリモザ 新人ギリモザ 蓮井志帆</title>

        <URL>http://www.dmm.co.jp/ppm/video/-/detail/=/cid=soe077/</URL>

        <affiliateURL>http://www.dmm.co.jp/ppm/video/-/detail/=/cid=soe077/affiliate-999</affiliateURL>

        <imageURL>

          <list>http://pics.dmm.co.jp/digital/video/soe00077/soe00077pt.jpg</list>

          <small>http://pics.dmm.co.jp/digital/video/soe00077/soe00077ps.jpg</small>

          <large>http://pics.dmm.co.jp/digital/video/soe00077/soe00077pl.jpg</large>

        </imageURL>

        <prices>

          <price>70</price>

        </prices>

        <date>2009-01-07 10:00:25</date>

        <iteminfo>

          <keyword>

            <name>デビュー作品</name>

            <id>6006</id>

          </keyword>

          <keyword>

            <name>3P・4P</name>

            <id>5022</id>

          </keyword>

          <keyword>

            <name>騎乗位</name>

            <id>4106</id>

          </keyword>

          <keyword>

            <name>指マン</name>

            <id>5053</id>

          </keyword>

          <keyword>

            <name>ギリモザ</name>

            <id>6017</id>

          </keyword>

          <keyword>

            <name>独占配信</name>

            <id>6548</id>

          </keyword>

          <series>

            <name>新人×ギリギリモザイク</name>

            <id>3454</id>

          </series>

          <maker>

            <name>エスワン ナンバーワンスタイル</name>

            <id>3152</id>

          </maker>

          <actress>

            <name>蓮井志帆</name>

            <id>27095</id>

          </actress>

          <actress>

            <name>はすいしほ</name>

            <id>27095_ruby</id>

          </actress>

          <actress>

            <name>av</name>

            <id>27095_classify</id>

          </actress>

          <director>

            <name>石橋渉</name>

            <id>101151</id>

          </director>

          <director>

            <name>いしばしわたる</name>

            <id>101151_ruby</id>

          </director>

          <label>

            <name>S1 NO.1 STYLE</name>

            <id>3474</id>

          </label>

        </iteminfo>

      </item>

      <item>

        <service_name>1円動画</service_name>

        <floor_name>ビデオ</floor_name>

        <category_name>ビデオ (1円動画)</category_name>

        <content_id>onsd00539</content_id>

        <product_id>onsd00539</product_id>

        <title>蒼井そら エスワン12時間 Special</title>

        <URL>http://www.dmm.co.jp/ppm/video/-/detail/=/cid=onsd00539/</URL>

        <affiliateURL>http://www.dmm.co.jp/ppm/video/-/detail/=/cid=onsd00539/affiliate-999</affiliateURL>

        <imageURL>

          <list>http://pics.dmm.co.jp/digital/video/onsd00539/onsd00539pt.jpg</list>

          <small>http://pics.dmm.co.jp/digital/video/onsd00539/onsd00539ps.jpg</small>

          <large>http://pics.dmm.co.jp/digital/video/onsd00539/onsd00539pl.jpg</large>

        </imageURL>

        <prices>

          <price>70</price>

        </prices>

        <date>2011-11-19 10:00:02</date>

        <iteminfo>

          <keyword>

            <name>独占配信</name>

            <id>6548</id>

          </keyword>

          <keyword>

            <name>ギリモザ</name>

            <id>6017</id>

          </keyword>

          <keyword>

            <name>4時間以上作品</name>

            <id>6012</id>

          </keyword>

          <keyword>

            <name>ベスト・総集編</name>

            <id>6003</id>

          </keyword>

          <keyword>

            <name>単体作品</name>

            <id>4025</id>

          </keyword>

          <keyword>

            <name>巨乳</name>

            <id>2001</id>

          </keyword>

          <series>

            <name>S1 GIRLS COLLECTION</name>

            <id>5087</id>

          </series>

          <maker>

            <name>エスワン ナンバーワンスタイル</name>

            <id>3152</id>

          </maker>

          <actress>

            <name>蒼井そら</name>

            <id>3996</id>

          </actress>

          <actress>

            <name>あおいそら</name>

            <id>3996_ruby</id>

          </actress>

          <actress>

            <name>av</name>

            <id>3996_classify</id>

          </actress>

          <label>

            <name>S1 NO.1 STYLE</name>

            <id>3474</id>

          </label>

        </iteminfo>

      </item>

      <item>

        <service_name>1円動画</service_name>

        <floor_name>ビデオ</floor_name>

        <category_name>ビデオ (1円動画)</category_name>

        <content_id>soe108</content_id>

        <product_id>soe00108</product_id>

        <title>悩殺BODY×ギリモザ 新人ギリモザ 女池さゆり</title>

        <URL>http://www.dmm.co.jp/ppm/video/-/detail/=/cid=soe108/</URL>

        <affiliateURL>http://www.dmm.co.jp/ppm/video/-/detail/=/cid=soe108/affiliate-999</affiliateURL>

        <imageURL>

          <list>http://pics.dmm.co.jp/digital/video/soe00108/soe00108pt.jpg</list>

          <small>http://pics.dmm.co.jp/digital/video/soe00108/soe00108ps.jpg</small>

          <large>http://pics.dmm.co.jp/digital/video/soe00108/soe00108pl.jpg</large>

        </imageURL>

        <prices>

          <price>70</price>

        </prices>

        <date>2009-02-19 10:00:25</date>

        <iteminfo>

          <keyword>

            <name>ギリモザ</name>

            <id>6017</id>

          </keyword>

          <keyword>

            <name>顔射</name>

            <id>5023</id>

          </keyword>

          <keyword>

            <name>3P・4P</name>

            <id>5022</id>

          </keyword>

          <keyword>

            <name>パイズリ</name>

            <id>5019</id>

          </keyword>

          <keyword>

            <name>デビュー作品</name>

            <id>6006</id>

          </keyword>

          <keyword>

            <name>独占配信</name>

            <id>6548</id>

          </keyword>

          <series>

            <name>新人×ギリギリモザイク</name>

            <id>3454</id>

          </series>

          <maker>

            <name>エスワン ナンバーワンスタイル</name>

            <id>3152</id>

          </maker>

          <actress>

            <name>女池さゆり</name>

            <id>27604</id>

          </actress>

          <actress>

            <name>めいけさゆり</name>

            <id>27604_ruby</id>

          </actress>

          <actress>

            <name>av</name>

            <id>27604_classify</id>

          </actress>

          <director>

            <name>中目黒浩治</name>

            <id>101154</id>

          </director>

          <director>

            <name>なかめぐろこうじ</name>

            <id>101154_ruby</id>

          </director>

          <label>

            <name>S1 NO.1 STYLE</name>

            <id>3474</id>

          </label>

        </iteminfo>

      </item>

      <item>

        <service_name>1円動画</service_name>

        <floor_name>ビデオ</floor_name>

        <category_name>ビデオ (1円動画)</category_name>

        <content_id>1sdmt00036</content_id>

        <product_id>1sdmt00036</product_id>

        <title>素人娘がギリギリモザイクフェラでザーメンお口で受け止めて 厳選美少女！！チ○ポに恥じらい初めてのフェラでザーメンを味わう！！</title>

        <URL>http://www.dmm.co.jp/ppm/video/-/detail/=/cid=1sdmt00036/</URL>

        <affiliateURL>http://www.dmm.co.jp/ppm/video/-/detail/=/cid=1sdmt00036/affiliate-999</affiliateURL>

        <imageURL>

          <list>http://pics.dmm.co.jp/digital/video/1sdmt00036/1sdmt00036pt.jpg</list>

          <small>http://pics.dmm.co.jp/digital/video/1sdmt00036/1sdmt00036ps.jpg</small>

          <large>http://pics.dmm.co.jp/digital/video/1sdmt00036/1sdmt00036pl.jpg</large>

        </imageURL>

        <prices>

          <price>30</price>

        </prices>

        <date>2011-03-21 10:00:00</date>

        <iteminfo>

          <keyword>

            <name>デジモ</name>

            <id>6004</id>

          </keyword>

          <keyword>

            <name>ギリモザ</name>

            <id>6017</id>

          </keyword>

          <keyword>

            <name>フェラ</name>

            <id>5002</id>

          </keyword>

          <keyword>

            <name>素人</name>

            <id>4024</id>

          </keyword>

          <keyword>

            <name>その他フェチ</name>

            <id>4010</id>

          </keyword>

          <series>

            <name>素人娘</name>

            <id>70867</id>

          </series>

          <maker>

            <name>SODクリエイト</name>

            <id>45276</id>

          </maker>

          <director>

            <name>藤丼博之</name>

            <id>102823</id>

          </director>

          <director>

            <name>ふじどんひろゆき</name>

            <id>102823_ruby</id>

          </director>

          <label>

            <name>SODクリエイト</name>

            <id>4130</id>

          </label>

        </iteminfo>

      </item>

      <item>

        <service_name>1円動画</service_name>

        <floor_name>ビデオ</floor_name>

        <category_name>ビデオ (1円動画)</category_name>

        <content_id>1sdms00852</content_id>

        <product_id>1sdms00852</product_id>

        <title>素人娘がギリギリモザイクフェラで最後はザーメン口内発射！5</title>

        <URL>http://www.dmm.co.jp/ppm/video/-/detail/=/cid=1sdms00852/</URL>

        <affiliateURL>http://www.dmm.co.jp/ppm/video/-/detail/=/cid=1sdms00852/affiliate-999</affiliateURL>

        <imageURL>

          <list>http://pics.dmm.co.jp/digital/video/1sdms00852/1sdms00852pt.jpg</list>

          <small>http://pics.dmm.co.jp/digital/video/1sdms00852/1sdms00852ps.jpg</small>

          <large>http://pics.dmm.co.jp/digital/video/1sdms00852/1sdms00852pl.jpg</large>

        </imageURL>

        <prices>

          <price>30</price>

        </prices>

        <date>2011-03-06 10:00:00</date>

        <iteminfo>

          <keyword>

            <name>フェラ</name>

            <id>5002</id>

          </keyword>

          <keyword>

            <name>素人</name>

            <id>4024</id>

          </keyword>

          <keyword>

            <name>デジモ</name>

            <id>6004</id>

          </keyword>

          <keyword>

            <name>その他フェチ</name>

            <id>4010</id>

          </keyword>

          <series>

            <name>素人娘</name>

            <id>70867</id>

          </series>

          <maker>

            <name>SODクリエイト</name>

            <id>45276</id>

          </maker>

          <director>

            <name>藤丼博之</name>

            <id>102823</id>

          </director>

          <director>

            <name>ふじどんひろゆき</name>

            <id>102823_ruby</id>

          </director>

          <label>

            <name>SOFT ON DEMAND</name>

            <id>125</id>

          </label>

        </iteminfo>

      </item>

      <item>

        <service_name>1円動画</service_name>

        <floor_name>ビデオ</floor_name>

        <category_name>ビデオ (1円動画)</category_name>

        <content_id>soe163</content_id>

        <product_id>soe00163</product_id>

        <title>了解×ギリモザ 新人ギリモザ 恵けい</title>

        <URL>http://www.dmm.co.jp/ppm/video/-/detail/=/cid=soe163/</URL>

        <affiliateURL>http://www.dmm.co.jp/ppm/video/-/detail/=/cid=soe163/affiliate-999</affiliateURL>

        <imageURL>

          <list>http://pics.dmm.co.jp/digital/video/soe00163/soe00163pt.jpg</list>

          <small>http://pics.dmm.co.jp/digital/video/soe00163/soe00163ps.jpg</small>

          <large>http://pics.dmm.co.jp/digital/video/soe00163/soe00163pl.jpg</large>

        </imageURL>

        <prices>

          <price>70</price>

        </prices>

        <date>2009-05-07 10:00:19</date>

        <iteminfo>

          <keyword>

            <name>巨乳</name>

            <id>2001</id>

          </keyword>

          <keyword>

            <name>ギリモザ</name>

            <id>6017</id>

          </keyword>

          <keyword>

            <name>ローション</name>

            <id>5057</id>

          </keyword>

          <keyword>

            <name>指マン</name>

            <id>5053</id>

          </keyword>

          <keyword>

            <name>潮吹き</name>

            <id>5016</id>

          </keyword>

          <keyword>

            <name>独占配信</name>

            <id>6548</id>

          </keyword>

          <series>

            <name>新人×ギリギリモザイク</name>

            <id>3454</id>

          </series>

          <maker>

            <name>エスワン ナンバーワンスタイル</name>

            <id>3152</id>

          </maker>

          <actress>

            <name>恵けい</name>

            <id>26488</id>

          </actress>

          <actress>

            <name>めぐみけい</name>

            <id>26488_ruby</id>

          </actress>

          <actress>

            <name>av</name>

            <id>26488_classify</id>

          </actress>

          <director>

            <name>愛染知久</name>

            <id>101252</id>

          </director>

          <director>

            <name>あいぞめともひさ</name>

            <id>101252_ruby</id>

          </director>

          <label>

            <name>S1 NO.1 STYLE</name>

            <id>3474</id>

          </label>

        </iteminfo>

      </item>

      <item>

        <service_name>1円動画</service_name>

        <floor_name>ビデオ</floor_name>

        <category_name>ビデオ (1円動画)</category_name>

        <content_id>soe131</content_id>

        <product_id>soe00131</product_id>

        <title>了解×ギリモザ 新人ギリモザ 長澤あずさ</title>

        <URL>http://www.dmm.co.jp/ppm/video/-/detail/=/cid=soe131/</URL>

        <affiliateURL>http://www.dmm.co.jp/ppm/video/-/detail/=/cid=soe131/affiliate-999</affiliateURL>

        <imageURL>

          <list>http://pics.dmm.co.jp/digital/video/soe00131/soe00131pt.jpg</list>

          <small>http://pics.dmm.co.jp/digital/video/soe00131/soe00131ps.jpg</small>

          <large>http://pics.dmm.co.jp/digital/video/soe00131/soe00131pl.jpg</large>

        </imageURL>

        <prices>

          <price>70</price>

        </prices>

        <date>2009-03-19 10:00:34</date>

        <iteminfo>

          <keyword>

            <name>顔射</name>

            <id>5023</id>

          </keyword>

          <keyword>

            <name>パイズリ</name>

            <id>5019</id>

          </keyword>

          <keyword>

            <name>ギリモザ</name>

            <id>6017</id>

          </keyword>

          <keyword>

            <name>騎乗位</name>

            <id>4106</id>

          </keyword>

          <keyword>

            <name>巨乳</name>

            <id>2001</id>

          </keyword>

          <keyword>

            <name>独占配信</name>

            <id>6548</id>

          </keyword>

          <series>

            <name>新人×ギリギリモザイク</name>

            <id>3454</id>

          </series>

          <maker>

            <name>エスワン ナンバーワンスタイル</name>

            <id>3152</id>

          </maker>

          <actress>

            <name>長澤あずさ</name>

            <id>26278</id>

          </actress>

          <actress>

            <name>ながさわあずさ</name>

            <id>26278_ruby</id>

          </actress>

          <actress>

            <name>av</name>

            <id>26278_classify</id>

          </actress>

          <director>

            <name>石橋渉</name>

            <id>101151</id>

          </director>

          <director>

            <name>いしばしわたる</name>

            <id>101151_ruby</id>

          </director>

          <label>

            <name>S1 NO.1 STYLE</name>

            <id>3474</id>

          </label>

        </iteminfo>

      </item>

      <item>

        <service_name>1円動画</service_name>

        <floor_name>ビデオ</floor_name>

        <category_name>ビデオ (1円動画)</category_name>

        <content_id>soe066</content_id>

        <product_id>soe00066</product_id>

        <title>了解×ギリモザ 新人ギリモザ あのあるる</title>

        <URL>http://www.dmm.co.jp/ppm/video/-/detail/=/cid=soe066/</URL>

        <affiliateURL>http://www.dmm.co.jp/ppm/video/-/detail/=/cid=soe066/affiliate-999</affiliateURL>

        <imageURL>

          <list>http://pics.dmm.co.jp/digital/video/soe00066/soe00066pt.jpg</list>

          <small>http://pics.dmm.co.jp/digital/video/soe00066/soe00066ps.jpg</small>

          <large>http://pics.dmm.co.jp/digital/video/soe00066/soe00066pl.jpg</large>

        </imageURL>

        <prices>

          <price>70</price>

        </prices>

        <date>2008-12-19 10:00:18</date>

        <iteminfo>

          <keyword>

            <name>巨乳</name>

            <id>2001</id>

          </keyword>

          <keyword>

            <name>パイズリ</name>

            <id>5019</id>

          </keyword>

          <keyword>

            <name>潮吹き</name>

            <id>5016</id>

          </keyword>

          <keyword>

            <name>顔射</name>

            <id>5023</id>

          </keyword>

          <keyword>

            <name>ギリモザ</name>

            <id>6017</id>

          </keyword>

          <keyword>

            <name>独占配信</name>

            <id>6548</id>

          </keyword>

          <series>

            <name>新人×ギリギリモザイク</name>

            <id>3454</id>

          </series>

          <maker>

            <name>エスワン ナンバーワンスタイル</name>

            <id>3152</id>

          </maker>

          <actress>

            <name>あのあるる</name>

            <id>25140</id>

          </actress>

          <actress>

            <name>あのあるる</name>

            <id>25140_ruby</id>

          </actress>

          <actress>

            <name>av</name>

            <id>25140_classify</id>

          </actress>

          <director>

            <name>ザック荒井</name>

            <id>290</id>

          </director>

          <director>

            <name>ざっくあらい</name>

            <id>290_ruby</id>

          </director>

          <label>

            <name>S1 NO.1 STYLE</name>

            <id>3474</id>

          </label>

        </iteminfo>

      </item>

      <item>

        <service_name>1円動画</service_name>

        <floor_name>ビデオ</floor_name>

        <category_name>ビデオ (1円動画)</category_name>

        <content_id>1sdmt00145</content_id>

        <product_id>1sdmt00145</product_id>

        <title>素人娘ギリギリモザイクフェラでザーメンお口で受け止めて</title>

        <URL>http://www.dmm.co.jp/ppm/video/-/detail/=/cid=1sdmt00145/</URL>

        <affiliateURL>http://www.dmm.co.jp/ppm/video/-/detail/=/cid=1sdmt00145/affiliate-999</affiliateURL>

        <imageURL>

          <list>http://pics.dmm.co.jp/digital/video/1sdmt00145/1sdmt00145pt.jpg</list>

          <small>http://pics.dmm.co.jp/digital/video/1sdmt00145/1sdmt00145ps.jpg</small>

          <large>http://pics.dmm.co.jp/digital/video/1sdmt00145/1sdmt00145pl.jpg</large>

        </imageURL>

        <prices>

          <price>30</price>

        </prices>

        <date>2011-02-22 10:00:00</date>

        <iteminfo>

          <keyword>

            <name>素人</name>

            <id>4024</id>

          </keyword>

          <keyword>

            <name>デジモ</name>

            <id>6004</id>

          </keyword>

          <keyword>

            <name>フェラ</name>

            <id>5002</id>

          </keyword>

          <keyword>

            <name>ナンパ</name>

            <id>4006</id>

          </keyword>

          <series>

            <name>素人娘</name>

            <id>70867</id>

          </series>

          <maker>

            <name>SODクリエイト</name>

            <id>45276</id>

          </maker>

          <director>

            <name>藤丼博之</name>

            <id>102823</id>

          </director>

          <director>

            <name>ふじどんひろゆき</name>

            <id>102823_ruby</id>

          </director>

          <label>

            <name>SODクリエイト</name>

            <id>4130</id>

          </label>

        </iteminfo>

      </item>

      <item>

        <service_name>1円動画</service_name>

        <floor_name>ビデオ</floor_name>

        <category_name>ビデオ (1円動画)</category_name>

        <content_id>1star00275</content_id>

        <product_id>1star00275</product_id>

        <title>えげつない体位と超極小モザイクで堪能する 過激ネットアイドル 片桐えりりか</title>

        <URL>http://www.dmm.co.jp/ppm/video/-/detail/=/cid=1star00275/</URL>

        <affiliateURL>http://www.dmm.co.jp/ppm/video/-/detail/=/cid=1star00275/affiliate-999</affiliateURL>

        <imageURL>

          <list>http://pics.dmm.co.jp/digital/video/1star00275/1star00275pt.jpg</list>

          <small>http://pics.dmm.co.jp/digital/video/1star00275/1star00275ps.jpg</small>

          <large>http://pics.dmm.co.jp/digital/video/1star00275/1star00275pl.jpg</large>

        </imageURL>

        <prices>

          <price>30</price>

        </prices>

        <date>2011-09-08 10:00:00</date>

        <iteminfo>

          <keyword>

            <name>3P・4P</name>

            <id>5022</id>

          </keyword>

          <keyword>

            <name>騎乗位</name>

            <id>4106</id>

          </keyword>

          <keyword>

            <name>単体作品</name>

            <id>4025</id>

          </keyword>

          <keyword>

            <name>アイドル・芸能人</name>

            <id>4118</id>

          </keyword>

          <keyword>

            <name>デジモ</name>

            <id>6004</id>

          </keyword>

          <series>

            <name>えげつない体位と超極小モザイクで堪能する○○</name>

            <id>200718</id>

          </series>

          <maker>

            <name>SODクリエイト</name>

            <id>45276</id>

          </maker>

          <actress>

            <name>片桐えりりか</name>

            <id>1010127</id>

          </actress>

          <actress>

            <name>かたぎりえりりか</name>

            <id>1010127_ruby</id>

          </actress>

          <actress>

            <name>av</name>

            <id>1010127_classify</id>

          </actress>

          <director>

            <name>宇佐美忠則</name>

            <id>101142</id>

          </director>

          <director>

            <name>うさみただのり</name>

            <id>101142_ruby</id>

          </director>

          <label>

            <name>SODクリエイト</name>

            <id>4130</id>

          </label>

        </iteminfo>

      </item>

      <item>

        <service_name>1円動画</service_name>

        <floor_name>ビデオ</floor_name>

        <category_name>ビデオ (1円動画)</category_name>

        <content_id>oned988</content_id>

        <product_id>oned00988</product_id>

        <title>ハイパー×ギリモザ パイパンハイパーギリモザ 小川あさ美</title>

        <URL>http://www.dmm.co.jp/ppm/video/-/detail/=/cid=oned988/</URL>

        <affiliateURL>http://www.dmm.co.jp/ppm/video/-/detail/=/cid=oned988/affiliate-999</affiliateURL>

        <imageURL>

          <list>http://pics.dmm.co.jp/digital/video/oned00988/oned00988pt.jpg</list>

          <small>http://pics.dmm.co.jp/digital/video/oned00988/oned00988ps.jpg</small>

          <large>http://pics.dmm.co.jp/digital/video/oned00988/oned00988pl.jpg</large>

        </imageURL>

        <prices>

          <price>70</price>

        </prices>

        <date>2008-11-12 10:00:00</date>

        <iteminfo>

          <keyword>

            <name>3P・4P</name>

            <id>5022</id>

          </keyword>

          <keyword>

            <name>単体作品</name>

            <id>4025</id>

          </keyword>

          <keyword>

            <name>パイパン</name>

            <id>4019</id>

          </keyword>

          <keyword>

            <name>ギリモザ</name>

            <id>6017</id>

          </keyword>

          <keyword>

            <name>独占配信</name>

            <id>6548</id>

          </keyword>

          <series>

            <name>ハイパーギリギリモザイク</name>

            <id>6542</id>

          </series>

          <maker>

            <name>エスワン ナンバーワンスタイル</name>

            <id>3152</id>

          </maker>

          <actress>

            <name>小川あさ美</name>

            <id>14827</id>

          </actress>

          <actress>

            <name>おがわあさみ</name>

            <id>14827_ruby</id>

          </actress>

          <actress>

            <name>av</name>

            <id>14827_classify</id>

          </actress>

          <director>

            <name>伊基公袁</name>

            <id>101141</id>

          </director>

          <director>

            <name>いぎーこーえん</name>

            <id>101141_ruby</id>

          </director>

          <label>

            <name>S1 NO.1 STYLE</name>

            <id>3474</id>

          </label>

        </iteminfo>

      </item>

    </items>

  </result>

</response>